litemind/__init__.py
litemind/agent/README.md
litemind/agent/__init__.py
litemind/agent/agent.py
litemind/agent/exceptions.py
litemind/agent/augmentations/__init__.py
litemind/agent/augmentations/augmentation_base.py
litemind/agent/augmentations/augmentation_default.py
litemind/agent/augmentations/augmentation_set.py
litemind/agent/augmentations/information/__init__.py
litemind/agent/augmentations/information/information.py
litemind/agent/augmentations/information/information_base.py
litemind/agent/augmentations/vector_db/__init__.py
litemind/agent/augmentations/vector_db/base_vector_db.py
litemind/agent/augmentations/vector_db/default_vector_db.py
litemind/agent/augmentations/vector_db/in_memory_vector_db.py
litemind/agent/augmentations/vector_db/qdrant_vector_db.py
litemind/agent/messages/__init__.py
litemind/agent/messages/conversation.py
litemind/agent/messages/message.py
litemind/agent/messages/message_block.py
litemind/agent/messages/actions/__init__.py
litemind/agent/messages/actions/action_base.py
litemind/agent/messages/actions/tool_call.py
litemind/agent/messages/actions/tool_use.py
litemind/agent/tools/__init__.py
litemind/agent/tools/agent_tool.py
litemind/agent/tools/base_tool.py
litemind/agent/tools/function_tool.py
litemind/agent/tools/toolset.py
litemind/agent/tools/builtin_tools/__init__.py
litemind/agent/tools/builtin_tools/builtin_tool.py
litemind/agent/tools/builtin_tools/mcp_tool.py
litemind/agent/tools/builtin_tools/web_search_tool.py
litemind/agent/tools/callbacks/__init__.py
litemind/agent/tools/callbacks/base_tool_callbacks.py
litemind/agent/tools/callbacks/print_api_callbacks.py
litemind/agent/tools/callbacks/tool_callback_manager.py
litemind/agent/tools/utils/__init__.py
litemind/agent/tools/utils/inspect_function.py
litemind/apis/README.md
litemind/apis/__init__.py
litemind/apis/base_api.py
litemind/apis/combined_api.py
litemind/apis/default_api.py
litemind/apis/error_handling.py
litemind/apis/exceptions.py
litemind-2026.1.29.1.dist-info/METADATA
litemind-2026.1.29.1.dist-info/WHEEL
litemind-2026.1.29.1.dist-info/entry_points.txt
litemind-2026.1.29.1.dist-info/licenses/LICENSE
litemind-2026.1.29.1.dist-info/RECORD
