Metadata-Version: 2.4
Name: litemind
Version: 2026.1.29.1
Summary: A wrapper API around LLM APIs and agentic AI framework
Project-URL: Homepage, https://github.com/royerlab/litemind
Project-URL: Issues, https://github.com/royerlab/litemind/issues
Author: Loic A. Royer
License-Expression: BSD-3-Clause
License-File: LICENSE
Keywords: agents,ai,llm,wrapper
Classifier: Development Status :: 4 - Beta
Classifier: Intended Audience :: Developers
Classifier: License :: OSI Approved :: BSD License
Classifier: Programming Language :: Python :: 3
Classifier: Programming Language :: Python :: 3.9
Classifier: Programming Language :: Python :: 3.10
Classifier: Programming Language :: Python :: 3.11
Classifier: Programming Language :: Python :: 3.12
Classifier: Programming Language :: Python :: 3.13
Requires-Python: >=3.9
Requires-Dist: absl-py
Requires-Dist: ansicolors
Requires-Dist: anthropic>=0.76.0
Requires-Dist: arbol
Requires-Dist: chardet
Requires-Dist: filetype
Requires-Dist: google-genai>=1.60.0
Requires-Dist: json-repair
Requires-Dist: numpy
Requires-Dist: ollama>=0.6.1
Requires-Dist: openai>=2.16.0
Requires-Dist: pandas
Requires-Dist: pillow
Requires-Dist: pydantic
Requires-Dist: python-magic
Requires-Dist: pyyaml
Requires-Dist: scipy
Requires-Dist: tiktoken
Provides-Extra: audio
Requires-Dist: soundfile; extra == 'audio'
Provides-Extra: build
Requires-Dist: build; extra == 'build'
Requires-Dist: hatch; extra == 'build'
Provides-Extra: dev
Requires-Dist: black[jupyter]; extra == 'dev'
Requires-Dist: flake8; extra == 'dev'
Requires-Dist: hatch; extra == 'dev'
Requires-Dist: isort; extra == 'dev'
Requires-Dist: mypy; extra == 'dev'
Requires-Dist: pypdf; extra == 'dev'
Requires-Dist: pytest; extra == 'dev'
Requires-Dist: pytest-cov; extra == 'dev'
Requires-Dist: pytest-html; extra == 'dev'
Requires-Dist: pytest-md-report; extra == 'dev'
Provides-Extra: documents
Requires-Dist: docling; extra == 'documents'
Requires-Dist: openpyxl; extra == 'documents'
Requires-Dist: pymupdf; extra == 'documents'
Requires-Dist: pymupdf4llm; extra == 'documents'
Requires-Dist: python-minifier; extra == 'documents'
Provides-Extra: rag
Requires-Dist: chromadb; extra == 'rag'
Requires-Dist: fastembed; extra == 'rag'
Requires-Dist: qdrant-client; extra == 'rag'
Provides-Extra: remote
Requires-Dist: rpyc; extra == 'remote'
Provides-Extra: tables
Requires-Dist: tabulate; extra == 'tables'
Provides-Extra: tasks
Requires-Dist: md2pdf; extra == 'tasks'
Provides-Extra: videos
Requires-Dist: ffmpeg-python; extra == 'videos'
Requires-Dist: imageio[ffmpeg]; extra == 'videos'
Provides-Extra: whisper
Requires-Dist: openai-whisper; extra == 'whisper'
